pygtrans/ApiKeyTranslate.py
pygtrans/DetectResponse.py
pygtrans/LanguageResponse.py
pygtrans/Null.py
pygtrans/Translate.py
pygtrans/TranslateResponse.py
pygtrans/__init__.py
pygtrans/__main__.py
pygtrans-1.6.2.dist-info/licenses/LICENSE
pygtrans-1.6.2.dist-info/METADATA
pygtrans-1.6.2.dist-info/WHEEL
pygtrans-1.6.2.dist-info/entry_points.txt
pygtrans-1.6.2.dist-info/top_level.txt
pygtrans-1.6.2.dist-info/RECORD
