Metadata-Version: 2.4
Name: pygtrans
Version: 1.6.2
Summary: Google Translate, support APIKEY
Author: foyoux
Project-URL: Source, https://github.com/foyoux/pygtrans
Project-URL: Homepage, https://github.com/foyoux/pygtrans
Project-URL: Bug Tracker, https://github.com/foyoux/pygtrans/issues
Keywords: pygtrans,google,translate,apikey,text,html,google.cn,google.com
Classifier: Programming Language :: Python :: 3
Classifier: Programming Language :: Python :: 3.6
Classifier: Programming Language :: Python :: 3.7
Classifier: Programming Language :: Python :: 3.8
Classifier: Programming Language :: Python :: 3.9
Classifier: Programming Language :: Python :: 3.10
Classifier: Programming Language :: Python :: 3.11
Classifier: Programming Language :: Python :: 3.12
Classifier: License :: OSI Approved :: GNU General Public License v3 (GPLv3)
Classifier: Environment :: Console
Classifier: Natural Language :: Chinese (Simplified)
Classifier: Development Status :: 5 - Production/Stable
Requires-Python: >=3.7
License-File: LICENSE
Requires-Dist: requests[socks]
Dynamic: license-file
